visier/__init__.py
visier/api/__init__.py
visier/api/base.py
visier/api/direct_intake.py
visier/api/dv_export.py
visier/api/intake.py
visier/api/model.py
visier/api/query.py
visier/connector/__init__.py
visier/connector/authentication.py
visier/connector/callback.py
visier/connector/constants.py
visier/connector/sessions.py
visier/connector/table.py
visier_connector-0.9.18.dist-info/LICENSE
visier_connector-0.9.18.dist-info/METADATA
visier_connector-0.9.18.dist-info/WHEEL
visier_connector-0.9.18.dist-info/top_level.txt
visier_connector-0.9.18.dist-info/RECORD
