Metadata-Version: 2.1
Name: visier-connector
Version: 0.9.18
Summary: Visier Python Connector
Author-email: Visier Research & Development <info@visier.com>
License: Apache License
Keywords: visier,data,query,connector,api
Requires-Python: >=3.8
License-File: LICENSE
Requires-Dist: requests >=2.31
Requires-Dist: deprecated
Requires-Dist: flask
Requires-Dist: python-dotenv
